tippecanoe/_version.py
tippecanoe/__init__.py
tippecanoe/share/man/man1/tippecanoe.1
tippecanoe/bin/tippecanoe-decode
tippecanoe/bin/tippecanoe-json-tool
tippecanoe/bin/tippecanoe
tippecanoe/bin/tippecanoe-overzoom
tippecanoe/bin/tile-join
tippecanoe/bin/tippecanoe-enumerate
tippecanoe.libs/libgcc_s-a04fdf82.so.1
tippecanoe.libs/libsqlite3-17acf9c1.so.0.8.6
tippecanoe.libs/libstdc++-a9383cce.so.6.0.28
tippecanoe-2.45.0.dist-info/METADATA
tippecanoe-2.45.0.dist-info/WHEEL
tippecanoe-2.45.0.dist-info/RECORD
tippecanoe-2.45.0.dist-info/entry_points.txt
