Metadata-Version: 2.1
Name: tippecanoe
Version: 2.45.0
Summary: Builds vector tilesets from large (or small) collections of GeoJSON, FlatGeobuf, or CSV features
Keywords: tags!
Author-Email: Ryan Mast <mast9@llnl.gov>
License: BSD License
Classifier: Development Status :: 5 - Production/Stable
Classifier: Environment :: Console
Classifier: Intended Audience :: Developers
Classifier: Intended Audience :: Science/Research
Classifier: Intended Audience :: End Users/Desktop
Classifier: License :: OSI Approved :: BSD License
Classifier: Natural Language :: English
Classifier: Operating System :: MacOS :: MacOS X
Classifier: Operating System :: POSIX :: Linux
Classifier: Operating System :: Unix
Classifier: Programming Language :: C
Classifier: Programming Language :: C++
Classifier: Programming Language :: Python
Classifier: Topic :: Software Development
Classifier: Topic :: Scientific/Engineering
Classifier: Topic :: Scientific/Engineering :: GIS
Classifier: Topic :: Utilities
Project-URL: Homepage, https://github.com/felt/tippecanoe
Project-URL: Download, https://github.com/felt/tippecanoe/releases
Project-URL: Issue tracker, https://github.com/felt/tippecanoe/issues
Project-URL: Source code, https://github.com/felt/tippecanoe
Requires-Python: >=3.7
